[
  {
    "id": 1,
    "name": "Banana",
    "category": "Dresses",
    "description": "You'll look stunning in this dress! Just like a happy banana in a tree.",
    "image": "@/assets/images/dresses/banana.jpg",
    "price": 29.99,
    "specifications": {
      "color": "Yellow",
      "size": "M",
      "material": "Cotton"
    },
    "reviews": [
      {
        "rating": 5,
        "comment": "So sexy",
        "author": "John Doe"
      },

      {
        "rating": 2,
        "comment": "Looks cheap",
        "author": "Amanda"
      },
      {
        "rating": 3,
        "comment": "OK",
        "author": "anonymous"
      }
    ]
  },
  {
    "id": 2,
    "name": "Butterfly",
    "category": "Dresses",
    "description": "Long dress with multicolor pattern. This dress will make you feel like a butterfly. It's light and airy.",
    "image": "@/assets/images/dresses/butterfly.jpg",
    "price": 39.99,
    "specifications": {
      "color": "Multi",
      "size": "S",
      "material": "Cotton"
    },
    "reviews": [
      {
        "rating": 5,
        "comment": "This is a great product",
        "author": "John Doe"
      },
      {
        "rating": 4,
        "comment": "This is a good product",
        "author": "Jane Doe"
      },
      {
        "rating": 2,
        "comment": "This is a product",
        "author": "Sam Doe"
      },
      {
        "rating": 1,
        "comment": "This is a bad product",
        "author": "Samantha Doe"
      }
    ]
  },
  {
    "id": 3,
    "name": "Leopard",
    "category": "Dresses",
    "description": "This is a midi dress with a leopard pattern.",
    "image": "path/to/leopard.jpg",
    "price": 99.99,
    "specifications": {
      "color": "Beige / Black",
      "size": "XS",
      "material": "Poly"
    },
    "reviews": [
      {
        "rating": 5,
        "comment": "This is a great product",
        "author": "John Doe"
      },
      {
        "rating": 4,
        "comment": "This is a good product",
        "author": "Jane Doe"
      },
      {
        "rating": 2,
        "comment": "This is a product",
        "author": "Sam Doe"
      },
      {
        "rating": 1,
        "comment": "This is a bad product",
        "author": "Samantha Doe"
      }
    ]
  },
  {
    "id": 4,
    "name": "Shawna",
    "category": "Dresses",
    "description": "A little peach colored delightful dress for the warmest summer days. It has a collar and a wrap tie.",
    "image": "path/to/shawna.jpg",
    "price": 199.99,
    "specifications": {
      "color": "Red",
      "size": "S",
      "material": "Msulin"
    },
    "reviews": [
      {
        "rating": 5,
        "comment": "This is a great product",
        "author": "John Doe"
      },
      {
        "rating": 4,
        "comment": "This is a good product",
        "author": "Jane Doe"
      },
      {
        "rating": 2,
        "comment": "This is a product",
        "author": "Sam Doe"
      },
      {
        "rating": 1,
        "comment": "This is a bad product",
        "author": "Samantha Doe"
      }
    ]
  }
]
